pyguilib/__init__.py
pyguilib/pyguilib.py
pyguilib/components/__init__.py
pyguilib/components/frame.py
pyguilib/components/image_label.py
pyguilib/components/pygui_instance.py
pyguilib/components/text_box.py
pyguilib/components/text_label.py
pyguilib/components/video_label.py
pyguilib/components/layouts/__init__.py
pyguilib/components/layouts/pygui_grid_layout.py
pyguilib/components/layouts/pygui_layout_container.py
pyguilib/components/layouts/pygui_layout_style.py
pyguilib/components/layouts/pygui_list_layout.py
pyguilib/services/__init__.py
pyguilib/services/action_service.py
pyguilib/services/tween_service.py
pyguilib/utilities/__init__.py
pyguilib/utilities/quadtree.py
pyguilib/utilities/signal.py
pyguilib/utilities/udim.py
pyguilib-0.0.5.dist-info/LICENSE
pyguilib-0.0.5.dist-info/METADATA
pyguilib-0.0.5.dist-info/WHEEL
pyguilib-0.0.5.dist-info/top_level.txt
pyguilib-0.0.5.dist-info/RECORD
