Metadata-Version: 2.1
Name: pyguilib
Version: 0.0.5
Summary: Graphical User Interface made for the Pygame multimedia applications library with the intention to facilitate the creation and/or management of the user interface.
Author-email: Guilherme Daghlian <gm.daghlian@gmail.com>
License: MIT License
Project-URL: Homepage, https://github.com/gmdvv2003/pyguilib
Keywords: Graphical User Interface,User Interface,PyGame,Game
Classifier: Development Status :: 3 - Alpha
Classifier: Operating System :: OS Independent
Classifier: License :: OSI Approved :: MIT License
Classifier: Programming Language :: Python :: 3
Requires-Python: >=3.8
License-File: LICENSE
Requires-Dist: pygame
Requires-Dist: imageio
